linebotx/__init__.py
linebotx/api.py
linebotx/http_client.py
linebotx/webhook.py
linebotx/commands/__init__.py
line_bot_sdk_extra-0.1.2.dist-info/LICENSE
line_bot_sdk_extra-0.1.2.dist-info/METADATA
line_bot_sdk_extra-0.1.2.dist-info/WHEEL
line_bot_sdk_extra-0.1.2.dist-info/top_level.txt
line_bot_sdk_extra-0.1.2.dist-info/RECORD
