Metadata-Version: 2.1
Name: line-bot-sdk-extra
Version: 0.1.2
Summary: Extra Async Support for LINE Messaging API SDK
Home-page: https://github.com/Shivelight/line-bot-sdk-extra
Author: Arkie
Author-email: cwkfr@protonmail.com
License: MIT
Platform: UNKNOWN
Classifier: Development Status :: 4 - Beta
Classifier: Intended Audience :: Developers
Classifier: License :: OSI Approved :: MIT License
Classifier: Programming Language :: Python
Classifier: Programming Language :: Python :: 3
Classifier: Programming Language :: Python :: 3.6
Classifier: Programming Language :: Python :: 3.7
Classifier: Programming Language :: Python :: Implementation :: CPython
Classifier: Topic :: Software Development
Classifier: Topic :: Software Development :: Libraries
Requires-Python: >=3.6.0
Requires-Dist: line-bot-sdk
Requires-Dist: aiohttp
